{
  "type": "FeatureCollection", 
  "features": [
    {
      "geometry": {
        "type": "Polygon", 
        "coordinates": [
          [
            [
              -79.92642689999997, 
              32.83271638900004
            ], 
            [
              -79.92676549299995, 
              32.83448135300006
            ], 
            [
              -79.92562335199995, 
              32.83733670600003
            ], 
            [
              -79.9254092, 
              32.839478221000036
            ], 
            [
              -79.92448121099994, 
              32.841548352000075
            ], 
            [
              -79.92440982699998, 
              32.843404331000045
            ], 
            [
              -79.92440982699998, 
              32.84511754300007
            ], 
            [
              -79.92476674599999, 
              32.84668798800004
            ], 
            [
              -79.92576611999993, 
              32.84854396700007
            ], 
            [
              -79.92705102899998, 
              32.85047133100005
            ], 
            [
              -79.92833593799998, 
              32.853326684000024
            ], 
            [
              -79.93026330099997, 
              32.85461159300007
            ], 
            [
              -79.93297588599995, 
              32.85553958300005
            ], 
            [
              -79.93447494699996, 
              32.857466946000045
            ], 
            [
              -79.93517974799994, 
              32.85893523800007
            ], 
            [
              -79.93528564799999, 
              32.859128070000054
            ], 
            [
              -79.93692362699994, 
              32.86211066000004
            ], 
            [
              -79.93728054599995, 
              32.86300295700005
            ], 
            [
              -79.93716157299997, 
              32.863478850000035
            ], 
            [
              -79.93676142699996, 
              32.864115355000024
            ], 
            [
              -79.93619035599994, 
              32.86402017700004
            ], 
            [
              -79.93466750099998, 
              32.863687052000046
            ], 
            [
              -79.93354915499998, 
              32.86347290100008
            ], 
            [
              -79.93283531599997, 
              32.86347290100008
            ], 
            [
              -79.93262116499994, 
              32.863139776000025
            ], 
            [
              -79.93183594299995, 
              32.86216419700003
            ], 
            [
              -79.93126487199999, 
              32.861831073000076
            ], 
            [
              -79.93076518499998, 
              32.862116608000065
            ], 
            [
              -79.93062241799998, 
              32.86278285700007
            ], 
            [
              -79.93033688199995, 
              32.863306339000076
            ], 
            [
              -79.93000375799994, 
              32.863544285000046
            ], 
            [
              -79.92945648199998, 
              32.86378223100007
            ], 
            [
              -79.92876643799997, 
              32.863972588000024
            ], 
            [
              -79.92833813499999, 
              32.864377096000055
            ], 
            [
              -79.92786224299994, 
              32.86518611300005
            ], 
            [
              -79.92748152899998, 
              32.86604271900006
            ], 
            [
              -79.92717219899998, 
              32.866399638000075
            ], 
            [
              -79.92688666399994, 
              32.86647102200004
            ], 
            [
              -79.92652974499998, 
              32.86644722700004
            ], 
            [
              -79.92641077199994, 
              32.86618548700005
            ], 
            [
              -79.92643456599995, 
              32.865709594000066
            ], 
            [
              -79.92631559299997, 
              32.86497196100004
            ], 
            [
              -79.92588728999993, 
              32.86430571200003
            ], 
            [
              -79.92543519299994, 
              32.863829820000035
            ], 
            [
              -79.92486412199997, 
              32.86347290100008
            ], 
            [
              -79.92424546199999, 
              32.863306339000076
            ], 
            [
              -79.92367439099996, 
              32.86321116000005
            ], 
            [
              -79.92322229399997, 
              32.86302080300004
            ], 
            [
              -79.92279399099993, 
              32.86302080300004
            ], 
            [
              -79.92260363399998, 
              32.86328254400007
            ], 
            [
              -79.92250845599995, 
              32.86356807900006
            ], 
            [
              -79.92265122299995, 
              32.86394879300008
            ], 
            [
              -79.92262742899999, 
              32.86440089100006
            ], 
            [
              -79.92191358999997, 
              32.86487678300006
            ], 
            [
              -79.92108077899996, 
              32.86547164800004
            ], 
            [
              -79.92053350299994, 
              32.86578097800003
            ], 
            [
              -79.92046211899998, 
              32.86616169200005
            ], 
            [
              -79.92077144899997, 
              32.866399638000075
            ], 
            [
              -79.92127113599997, 
              32.86642343300008
            ], 
            [
              -79.92155667099996, 
              32.86644722700004
            ], 
            [
              -79.92174702799997, 
              32.866542406000065
            ], 
            [
              -79.92165184999999, 
              32.86735142200007
            ], 
            [
              -79.92160425999998, 
              32.867970082000056
            ], 
            [
              -79.92193738499998, 
              32.869588116000045
            ], 
            [
              -79.92217533099995, 
              32.87018298100003
            ], 
            [
              -79.92210394699998, 
              32.87249105800004
            ], 
            [
              -79.92200876899994, 
              32.873752172000025
            ], 
            [
              -79.92158046599997, 
              32.87389494000007
            ], 
            [
              -79.92139010899996, 
              32.87413288600004
            ], 
            [
              -79.92139010899996, 
              32.874418422000076
            ], 
            [
              -79.92167564399995, 
              32.874656368000046
            ], 
            [
              -79.92177082299997, 
              32.87491810800003
            ], 
            [
              -79.92162805499999, 
              32.87541779500003
            ], 
            [
              -79.92131872499994, 
              32.87610783900004
            ], 
            [
              -79.92091421699996, 
              32.876964445000056
            ], 
            [
              -79.92027176199997, 
              32.877535515000034
            ], 
            [
              -79.91905823699994, 
              32.87732136400007
            ], 
            [
              -79.91782091699997, 
              32.87708341800004
            ], 
            [
              -79.91747153299997, 
              32.877815102000056
            ], 
            [
              -79.91729307399999, 
              32.87790433200007
            ], 
            [
              -79.91693615399998, 
              32.87739869600006
            ], 
            [
              -79.91672795199997, 
              32.877249980000045
            ], 
            [
              -79.91616282999996, 
              32.877249980000045
            ], 
            [
              -79.91595462699996, 
              32.87754741300006
            ], 
            [
              -79.91595462699996, 
              32.87805304800003
            ], 
            [
              -79.91595462699996, 
              32.878290994000054
            ], 
            [
              -79.91553822099996, 
              32.878647914000055
            ], 
            [
              -79.91553822099996, 
              32.87900483300007
            ], 
            [
              -79.91595462699996, 
              32.87918329200005
            ], 
            [
              -79.91672795199997, 
              32.879480725000064
            ], 
            [
              -79.91690641099996, 
              32.87974841400006
            ], 
            [
              -79.91663872199996, 
              32.880283793000046
            ], 
            [
              -79.91756076299998, 
              32.88162224000007
            ], 
            [
              -79.91762025, 
              32.88212787500004
            ], 
            [
              -79.91782845199998, 
              32.88284171400005
            ], 
            [
              -79.91827460099995, 
              32.88370426800003
            ], 
            [
              -79.91803665499998, 
              32.88435862000006
            ], 
            [
              -79.91524078899994, 
              32.88551860700005
            ], 
            [
              -79.91443771999997, 
              32.88593501300005
            ], 
            [
              -79.91295055699999, 
              32.88694628400003
            ], 
            [
              -79.91205825899993, 
              32.88816575800007
            ], 
            [
              -79.91170133999998, 
              32.888909339000065
            ], 
            [
              -79.91071981299996, 
              32.890158556000074
            ], 
            [
              -79.91003571799996, 
              32.89099136700003
            ], 
            [
              -79.90935162299996, 
              32.89122931400004
            ], 
            [
              -79.90872701399996, 
              32.89128880000004
            ], 
            [
              -79.90804291899997, 
              32.89108059700004
            ], 
            [
              -79.907686, 
              32.89063444800007
            ], 
            [
              -79.90703164799999, 
              32.890099070000076
            ], 
            [
              -79.90637729599996, 
              32.889742150000075
            ], 
            [
              -79.90578243099998, 
              32.889771894000035
            ], 
            [
              -79.90506859299995, 
              32.889980097000034
            ], 
            [
              -79.90444398399995, 
              32.890366759000074
            ], 
            [
              -79.90426552499997, 
              32.89090213800006
            ], 
            [
              -79.90438449799996, 
              32.89188366500008
            ], 
            [
              -79.90483064699998, 
              32.892805707000036
            ], 
            [
              -79.90497936299994, 
              32.89301390900005
            ], 
            [
              -79.90566345799994, 
              32.89348980200003
            ], 
            [
              -79.90670447199994, 
              32.89381697700003
            ], 
            [
              -79.90780497299994, 
              32.89417389700003
            ], 
            [
              -79.90884598699995, 
              32.89462004600006
            ], 
            [
              -79.90935162299996, 
              32.895095938000054
            ], 
            [
              -79.90970854199998, 
              32.89583951900005
            ], 
            [
              -79.90976802799997, 
              32.896493871000075
            ], 
            [
              -79.90905418999995, 
              32.896702074000075
            ], 
            [
              -79.90804291899997, 
              32.89667233100005
            ], 
            [
              -79.90331373999999, 
              32.897356426000044
            ], 
            [
              -79.90280810499996, 
              32.89789180400004
            ], 
            [
              -79.90203477999995, 
              32.89830821000004
            ], 
            [
              -79.90030967099995, 
              32.89925999400003
            ], 
            [
              -79.89914968299996, 
              32.899587170000075
            ], 
            [
              -79.89813841299997, 
              32.89970614300006
            ], 
            [
              -79.89751380399997, 
              32.89928973800005
            ], 
            [
              -79.89742457399996, 
              32.89848667000007
            ], 
            [
              -79.89688919599996, 
              32.897148223000045
            ], 
            [
              -79.89614561399998, 
              32.896077465000076
            ], 
            [
              -79.89522357299995, 
              32.89527439700004
            ], 
            [
              -79.89459896399995, 
              32.895095938000054
            ], 
            [
              -79.89376615299994, 
              32.89494722100005
            ], 
            [
              -79.89302257099996, 
              32.895304141000054
            ], 
            [
              -79.89275488199996, 
              32.89583951900005
            ], 
            [
              -79.89186258399997, 
              32.89741591200004
            ], 
            [
              -79.89135694899994, 
              32.89804052100004
            ], 
            [
              -79.89013747499996, 
              32.899616914000035
            ], 
            [
              -79.88918569099997, 
              32.90030100900003
            ], 
            [
              -79.88805544699994, 
              32.90050921200003
            ], 
            [
              -79.88534880999998, 
              32.90015229200003
            ], 
            [
              -79.88371292999994, 
              32.89946819700003
            ], 
            [
              -79.88317755099996, 
              32.898992305000036
            ], 
            [
              -79.88308832199994, 
              32.89774308800003
            ], 
            [
              -79.88290986199996, 
              32.89717796600007
            ], 
            [
              -79.88219602399994, 
              32.89524465400007
            ], 
            [
              -79.88136321199994, 
              32.89381697700003
            ], 
            [
              -79.88056014399996, 
              32.89194315200007
            ], 
            [
              -79.88014373899995, 
              32.89078316500007
            ], 
            [
              -79.87996527899998, 
              32.889325745000065
            ], 
            [
              -79.87954887299998, 
              32.887481663000074
            ], 
            [
              -79.87892426499997, 
              32.88614321600005
            ], 
            [
              -79.87838888599998, 
              32.88531040400005
            ], 
            [
              -79.87690172299995, 
              32.88290120000005
            ], 
            [
              -79.87657454699996, 
              32.88203864500008
            ], 
            [
              -79.87657454699996, 
              32.87942123800008
            ], 
            [
              -79.87660428999999, 
              32.876833575000035
            ], 
            [
              -79.87705043899996, 
              32.876000763000036
            ], 
            [
              -79.87746684499996, 
              32.875019235000025
            ], 
            [
              -79.87755607499997, 
              32.874126938000074
            ], 
            [
              -79.87767504799996, 
              32.873710532000075
            ], 
            [
              -79.87767504799996, 
              32.873323870000036
            ], 
            [
              -79.87782376399997, 
              32.87278849100005
            ], 
            [
              -79.8780617099999, 
              32.87243157200004
            ], 
            [
              -79.87904323799995, 
              32.872104396000054
            ], 
            [
              -79.87966784599996, 
              32.871925936000025
            ], 
            [
              -79.88097654999996, 
              32.87177722000007
            ], 
            [
              -79.88204730699994, 
              32.87201516600004
            ], 
            [
              -79.88377241699999, 
              32.87240182800008
            ], 
            [
              -79.88490266099996, 
              32.87249105800004
            ], 
            [
              -79.88564624199995, 
              32.872520801000064
            ], 
            [
              -79.88656828299997, 
              32.87237208500005
            ], 
            [
              -79.88737135099996, 
              32.87222336900004
            ], 
            [
              -79.88847185199995, 
              32.871717733000025
            ], 
            [
              -79.89004824499995, 
              32.870290057000034
            ], 
            [
              -79.89120823199994, 
              32.86933827200005
            ], 
            [
              -79.89165438099997, 
              32.868802894000055
            ], 
            [
              -79.89207078699997, 
              32.867821366000044
            ], 
            [
              -79.89224924699994, 
              32.867613163000044
            ], 
            [
              -79.89329026099995, 
              32.86645317600005
            ], 
            [
              -79.89462870799997, 
              32.865322932000026
            ], 
            [
              -79.89587792499998, 
              32.86446037700006
            ], 
            [
              -79.89662150599997, 
              32.86362756600005
            ], 
            [
              -79.89748406099994, 
              32.86300295700005
            ], 
            [
              -79.89801943899994, 
              32.86217014600004
            ], 
            [
              -79.89864404799994, 
              32.86166451100007
            ], 
            [
              -79.89968506199995, 
              32.86086144300003
            ], 
            [
              -79.90022044099999, 
              32.85970145500005
            ], 
            [
              -79.90141017099995, 
              32.857262508000076
            ], 
            [
              -79.90233221299997, 
              32.85550765500005
            ], 
            [
              -79.90236195599994, 
              32.85390151900003
            ], 
            [
              -79.90197529299996, 
              32.85190872000004
            ], 
            [
              -79.90173734699994, 
              32.85173026100006
            ], 
            [
              -79.90173734699994, 
              32.850540530000046
            ], 
            [
              -79.90105325199994, 
              32.845186743000056
            ], 
            [
              -79.89947685899995, 
              32.843164201000036
            ], 
            [
              -79.89914968299996, 
              32.841498579000074
            ], 
            [
              -79.89864404799994, 
              32.83917860400004
            ], 
            [
              -79.89858456099995, 
              32.83706683200006
            ], 
            [
              -79.89867379099996, 
              32.83549044000006
            ], 
            [
              -79.89909019699996, 
              32.834151993000035
            ], 
            [
              -79.90025018399996, 
              32.83117766600003
            ], 
            [
              -79.90141017099995, 
              32.829452557000025
            ], 
            [
              -79.90218349599996, 
              32.828381800000045
            ], 
            [
              -79.90825112199997, 
              32.82350390500005
            ], 
            [
              -79.91330747599994, 
              32.81928036100004
            ], 
            [
              -79.91842331799995, 
              32.81913164500003
            ], 
            [
              -79.92288480699995, 
              32.82127316000003
            ], 
            [
              -79.92359864499997, 
              32.82201674200007
            ], 
            [
              -79.92477816699994, 
              32.82327694700007
            ], 
            [
              -79.92499657899998, 
              32.82531824400007
            ], 
            [
              -79.92523502399996, 
              32.82681758500007
            ], 
            [
              -79.92540634499994, 
              32.828759225000056
            ], 
            [
              -79.92636476899997, 
              32.83150484200007
            ], 
            [
              -79.92642689999997, 
              32.83271638900004
            ]
          ]
        ]
      }, 
      "type": "Feature", 
      "properties": {
        "County": "Berkeley", 
        "City": "Charleston", 
        "State": "SC", 
        "RegionID": "51643", 
        "Name": "Daniel Island"
      }
    }, 
    {
      "geometry": {
        "type": "Polygon", 
        "coordinates": [
          [
            [
              -79.93503752599997, 
              32.74236936600005
            ], 
            [
              -79.93094098999995, 
              32.75150836700004
            ], 
            [
              -79.93041581599994, 
              32.75253985000006
            ], 
            [
              -79.93013197299996, 
              32.75316447200004
            ], 
            [
              -79.92941604999999, 
              32.75444513100007
            ], 
            [
              -79.92617403399998, 
              32.75358257600004
            ], 
            [
              -79.92578573599997, 
              32.75200347400005
            ], 
            [
              -79.9238540599999, 
              32.75111388500005
            ], 
            [
              -79.92430020799998, 
              32.75048927700004
            ], 
            [
              -79.92284278899996, 
              32.748407248000035
            ], 
            [
              -79.92302124799994, 
              32.74793135600004
            ], 
            [
              -79.92343765399994, 
              32.746503680000046
            ], 
            [
              -79.92364585699994, 
              32.74584932800008
            ], 
            [
              -79.92370534299994, 
              32.74564112500008
            ], 
            [
              -79.92495455999995, 
              32.74522471900008
            ], 
            [
              -79.92727453499998, 
              32.74457036800004
            ], 
            [
              -79.92840477899995, 
              32.74418370500007
            ], 
            [
              -79.92867246799995, 
              32.74361858300006
            ], 
            [
              -79.92882118399996, 
              32.74314269100006
            ], 
            [
              -79.92888067099994, 
              32.74236936600005
            ], 
            [
              -79.92888067099994, 
              32.74204219000006
            ], 
            [
              -79.93503752599997, 
              32.74236936600005
            ]
          ]
        ]
      }, 
      "type": "Feature", 
      "properties": {
        "County": "Charleston", 
        "City": "Charleston", 
        "State": "SC", 
        "RegionID": "223350", 
        "Name": "Stiles Point"
      }
    }, 
    {
      "geometry": {
        "type": "Polygon", 
        "coordinates": [
          [
            [
              -79.97887155999996, 
              32.780914652000035
            ], 
            [
              -79.97801495399995, 
              32.784602816000074
            ], 
            [
              -79.97799115999999, 
              32.785388038000065
            ], 
            [
              -79.97689660799995, 
              32.78567357400004
            ], 
            [
              -79.97608759099995, 
              32.78581634100004
            ], 
            [
              -79.97558790399995, 
              32.78633982300005
            ], 
            [
              -79.97489785999994, 
              32.78650638500005
            ], 
            [
              -79.97211389099994, 
              32.78610187700008
            ], 
            [
              -79.97258978299999, 
              32.78517388700004
            ], 
            [
              -79.97268496199996, 
              32.784555227000055
            ], 
            [
              -79.97254219399997, 
              32.78381759400003
            ], 
            [
              -79.97230424799994, 
              32.78329411300007
            ], 
            [
              -79.97206630199997, 
              32.782818220000024
            ], 
            [
              -79.97185214999996, 
              32.78241371200005
            ], 
            [
              -79.97137625799996, 
              32.781890231000034
            ], 
            [
              -79.97001996499995, 
              32.78115259800006
            ], 
            [
              -79.96804501299994, 
              32.780272197000045
            ], 
            [
              -79.96937751099995, 
              32.77970112600008
            ], 
            [
              -79.97001996499995, 
              32.779486975000054
            ], 
            [
              -79.97030550099998, 
              32.77932041300005
            ], 
            [
              -79.97073380399996, 
              32.779296618000046
            ], 
            [
              -79.97166179299995, 
              32.77955835900008
            ], 
            [
              -79.97887155999996, 
              32.780914652000035
            ]
          ]
        ]
      }, 
      "type": "Feature", 
      "properties": {
        "County": "Charleston", 
        "City": "Charleston", 
        "State": "SC", 
        "RegionID": "222257", 
        "Name": "Moreland"
      }
    }, 
    {
      "geometry": {
        "type": "Polygon", 
        "coordinates": [
          [
            [
              -80.00269450799993, 
              32.76025025000007
            ], 
            [
              -80.00143339399995, 
              32.76255832700008
            ], 
            [
              -80.00110026899995, 
              32.76408118200004
            ], 
            [
              -80.00117165299997, 
              32.76505676100004
            ], 
            [
              -80.00157616199994, 
              32.76617510800003
            ], 
            [
              -80.00162375099995, 
              32.76660341000007
            ], 
            [
              -80.00143339399995, 
              32.76684135700003
            ], 
            [
              -80.00007710099999, 
              32.767150687000026
            ], 
            [
              -79.99767384599994, 
              32.76750760600004
            ], 
            [
              -79.99619857999994, 
              32.767840730000046
            ], 
            [
              -79.99512782199997, 
              32.76779314100003
            ], 
            [
              -79.99462813499997, 
              32.76779314100003
            ], 
            [
              -79.99400947599997, 
              32.76767416800004
            ], 
            [
              -79.99346219999995, 
              32.76757899000006
            ], 
            [
              -79.99291492399999, 
              32.76800729200005
            ], 
            [
              -79.99236764799997, 
              32.76855456900006
            ], 
            [
              -79.99172519299998, 
              32.768768720000025
            ], 
            [
              -79.99141586299999, 
              32.76864974700004
            ], 
            [
              -79.99060684599993, 
              32.76786452500005
            ], 
            [
              -79.98986921299996, 
              32.76750760600004
            ], 
            [
              -79.98839394799995, 
              32.76686515100005
            ], 
            [
              -79.98765631499998, 
              32.76669858900004
            ], 
            [
              -79.98615725399998, 
              32.76536609100003
            ], 
            [
              -79.98639519999995, 
              32.76389082500003
            ], 
            [
              -79.98553859399993, 
              32.76358149500004
            ], 
            [
              -79.98532444299997, 
              32.76322457600003
            ], 
            [
              -79.98537203199999, 
              32.76260591600004
            ], 
            [
              -79.98817979599994, 
              32.76232038100005
            ], 
            [
              -79.98894122399997, 
              32.76191587200003
            ], 
            [
              -79.98960747299998, 
              32.76113065000004
            ], 
            [
              -79.99024992699998, 
              32.76070234700006
            ], 
            [
              -79.99110653299994, 
              32.76015507100004
            ], 
            [
              -79.99205831799998, 
              32.759536411000056
            ], 
            [
              -79.99312907499996, 
              32.758893957000055
            ], 
            [
              -79.99360496699995, 
              32.75858462700006
            ], 
            [
              -79.99415224299997, 
              32.75872739500005
            ], 
            [
              -79.99534197399998, 
              32.75827529700007
            ], 
            [
              -79.99619857999994, 
              32.75777561000007
            ], 
            [
              -79.99700759599995, 
              32.75734730700003
            ], 
            [
              -79.99776902399998, 
              32.75680003100007
            ], 
            [
              -79.99838768399997, 
              32.75641931700005
            ], 
            [
              -79.99883978099996, 
              32.75632413900007
            ], 
            [
              -79.99952982499997, 
              32.75668105800003
            ], 
            [
              -80.00064817199996, 
              32.758108735000064
            ], 
            [
              -79.99998192299995, 
              32.75846565400008
            ], 
            [
              -79.99983915499996, 
              32.76020266000006
            ], 
            [
              -79.99976777099994, 
              32.76086890900007
            ], 
            [
              -80.00038643099998, 
              32.76055958000006
            ], 
            [
              -80.00198066999997, 
              32.75946502700003
            ], 
            [
              -80.00255174099993, 
              32.759940920000076
            ], 
            [
              -80.00269450799993, 
              32.76025025000007
            ]
          ]
        ]
      }, 
      "type": "Feature", 
      "properties": {
        "County": "Charleston", 
        "City": "Charleston", 
        "State": "SC", 
        "RegionID": "222943", 
        "Name": "Riverland Terrace"
      }
    }, 
    {
      "geometry": {
        "type": "Polygon", 
        "coordinates": [
          [
            [
              -80.08769274699995, 
              32.84628308900005
            ], 
            [
              -80.08163119599999, 
              32.851477799000065
            ], 
            [
              -80.08163119599999, 
              32.851489696000044
            ], 
            [
              -80.08211694699997, 
              32.851930623000044
            ], 
            [
              -80.07652997299994, 
              32.856699063000065
            ], 
            [
              -80.07641112799996, 
              32.85663412500003
            ], 
            [
              -80.07493556199995, 
              32.85783746000004
            ], 
            [
              -80.07272963299994, 
              32.85595356500005
            ], 
            [
              -80.06699988999998, 
              32.85104235700004
            ], 
            [
              -80.06414453699995, 
              32.84864386100003
            ], 
            [
              -80.05814829599996, 
              32.843561332000036
            ], 
            [
              -80.05611092599997, 
              32.841837148000025
            ], 
            [
              -80.05928036799997, 
              32.83943865100008
            ], 
            [
              -80.06161279099996, 
              32.841848120000066
            ], 
            [
              -80.06277396799999, 
              32.840858264000076
            ], 
            [
              -80.06026125699998, 
              32.83876433800003
            ], 
            [
              -80.06793263899993, 
              32.833967345000076
            ], 
            [
              -80.06891297699997, 
              32.83352000600007
            ], 
            [
              -80.06913188799996, 
              32.83375795300003
            ], 
            [
              -80.06945549399995, 
              32.83401493400004
            ], 
            [
              -80.06951260099999, 
              32.834205291000046
            ], 
            [
              -80.06951260099999, 
              32.83437661200003
            ], 
            [
              -80.06948404799994, 
              32.83472877300005
            ], 
            [
              -80.06956018999995, 
              32.834881058000065
            ], 
            [
              -80.07005511799997, 
              32.83541405700004
            ], 
            [
              -80.07044534999994, 
              32.83577573500003
            ], 
            [
              -80.07069281399998, 
              32.83592802100003
            ], 
            [
              -80.07097834899997, 
              32.83608030600004
            ], 
            [
              -80.07124484899998, 
              32.83627066300005
            ], 
            [
              -80.07139713399994, 
              32.83644198500008
            ], 
            [
              -80.07170170499995, 
              32.83683221600006
            ], 
            [
              -80.07194916899994, 
              32.83713678700008
            ], 
            [
              -80.07252024, 
              32.837764965000076
            ], 
            [
              -80.07325311399995, 
              32.83857398200007
            ], 
            [
              -80.07403357699997, 
              32.83922119500005
            ], 
            [
              -80.07499012099998, 
              32.83967329300003
            ], 
            [
              -80.07546601299998, 
              32.83972088200005
            ], 
            [
              -80.07644159199998, 
              32.83943534600007
            ], 
            [
              -80.07738391599997, 
              32.839178349000065
            ], 
            [
              -80.07794010099997, 
              32.83901272800006
            ], 
            [
              -80.07826727699995, 
              32.838667706000024
            ], 
            [
              -80.07855281199994, 
              32.838560630000075
            ], 
            [
              -80.07907740399997, 
              32.83843621500006
            ], 
            [
              -80.07948675099993, 
              32.83806689200003
            ], 
            [
              -80.08012975599996, 
              32.83803146400004
            ], 
            [
              -80.08215229799998, 
              32.83991123900006
            ], 
            [
              -80.08286885699994, 
              32.84176556600005
            ], 
            [
              -80.08333523099998, 
              32.842526993000035
            ], 
            [
              -80.08515041899994, 
              32.84414667900006
            ], 
            [
              -80.08769274699995, 
              32.84628308900005
            ]
          ]
        ]
      }, 
      "type": "Feature", 
      "properties": {
        "County": "Charleston", 
        "City": "Charleston", 
        "State": "SC", 
        "RegionID": "223143", 
        "Name": "Shadowmoss"
      }
    }, 
    {
      "geometry": {
        "type": "Polygon", 
        "coordinates": [
          [
            [
              -79.95191702399995, 
              32.80001483700005
            ], 
            [
              -79.95063784999996, 
              32.79754235200005
            ], 
            [
              -79.95739551899999, 
              32.794038596000064
            ], 
            [
              -79.95894216899995, 
              32.79641805700004
            ], 
            [
              -79.95191702399995, 
              32.80001483700005
            ]
          ]
        ]
      }, 
      "type": "Feature", 
      "properties": {
        "County": "Charleston", 
        "City": "Charleston", 
        "State": "SC", 
        "RegionID": "762360", 
        "Name": "Hampton Park Terrace"
      }
    }, 
    {
      "geometry": {
        "type": "Polygon", 
        "coordinates": [
          [
            [
              -79.97373198299994, 
              32.775481014000036
            ], 
            [
              -79.98217470699996, 
              32.76815197700006
            ], 
            [
              -79.98474882899995, 
              32.77257315400004
            ], 
            [
              -79.98439190999994, 
              32.77439344100003
            ], 
            [
              -79.98464175299995, 
              32.77500020400004
            ], 
            [
              -79.98507005599998, 
              32.77535712300005
            ], 
            [
              -79.98549835899996, 
              32.77564265800004
            ], 
            [
              -79.98571251099997, 
              32.77603526900003
            ], 
            [
              -79.98163768399996, 
              32.77865862500005
            ], 
            [
              -79.97363674599995, 
              32.77746889500003
            ], 
            [
              -79.97373198299994, 
              32.775481014000036
            ]
          ]
        ]
      }, 
      "type": "Feature", 
      "properties": {
        "County": "Charleston", 
        "City": "Charleston", 
        "State": "SC", 
        "RegionID": "762408", 
        "Name": "South Windenere"
      }
    }, 
    {
      "geometry": {
        "type": "Polygon", 
        "coordinates": [
          [
            [
              -79.99351885399994, 
              32.81614509700006
            ], 
            [
              -79.99230532899998, 
              32.82026156400008
            ], 
            [
              -79.99194840999996, 
              32.82040433200007
            ], 
            [
              -79.98631948999997, 
              32.82157321200003
            ], 
            [
              -79.98623025999996, 
              32.821305523000035
            ], 
            [
              -79.98617674299999, 
              32.82115603500006
            ], 
            [
              -79.98454084299993, 
              32.819895692000046
            ], 
            [
              -79.98427300699996, 
              32.81974128200005
            ], 
            [
              -79.98400546399995, 
              32.81979456500005
            ], 
            [
              -79.98212123599995, 
              32.81850076300003
            ], 
            [
              -79.98197846799997, 
              32.81781071900008
            ], 
            [
              -79.98200226299997, 
              32.817239649000044
            ], 
            [
              -79.98238297699999, 
              32.81643063200005
            ], 
            [
              -79.98295404699996, 
              32.815716794000025
            ], 
            [
              -79.98340614499995, 
              32.81512192800005
            ], 
            [
              -79.98409618899996, 
              32.81459844700004
            ], 
            [
              -79.98433413499998, 
              32.81395599200005
            ], 
            [
              -79.98597596299999, 
              32.813718046000076
            ], 
            [
              -79.98852168099995, 
              32.81207662500003
            ], 
            [
              -79.98910940799999, 
              32.813140402000045
            ], 
            [
              -79.98968523799994, 
              32.81413961700002
            ], 
            [
              -79.99015140099993, 
              32.814420796000036
            ], 
            [
              -79.99083006299998, 
              32.81481259800006
            ], 
            [
              -79.99150314599996, 
              32.81515088800006
            ], 
            [
              -79.99230532899998, 
              32.81569299900008
            ], 
            [
              -79.99298793, 
              32.81607887800004
            ], 
            [
              -79.99351885399994, 
              32.81614509700006
            ]
          ]
        ]
      }, 
      "type": "Feature", 
      "properties": {
        "County": "Charleston", 
        "City": "Charleston", 
        "State": "SC", 
        "RegionID": "762410", 
        "Name": "Northbridge Terrace"
      }
    }, 
    {
      "geometry": {
        "type": "Polygon", 
        "coordinates": [
          [
            [
              -79.93180677999999, 
              32.79191600900003
            ], 
            [
              -79.93152278699995, 
              32.791730796000024
            ], 
            [
              -79.93184996299993, 
              32.791284647000055
            ], 
            [
              -79.93374877299993, 
              32.791941379000036
            ], 
            [
              -79.93406286199996, 
              32.79245534200004
            ], 
            [
              -79.93729422899997, 
              32.79125668900008
            ], 
            [
              -79.93914069099998, 
              32.79415011300006
            ], 
            [
              -79.94096811699995, 
              32.79690552900007
            ], 
            [
              -79.94077294199997, 
              32.79756047600006
            ], 
            [
              -79.9401185899999, 
              32.79815534100004
            ], 
            [
              -79.93964269799994, 
              32.79842303000004
            ], 
            [
              -79.93952372499996, 
              32.79883943600004
            ], 
            [
              -79.93559761399996, 
              32.80011839600007
            ], 
            [
              -79.93473506, 
              32.799523531000034
            ], 
            [
              -79.93280174799997, 
              32.79544870400008
            ], 
            [
              -79.93527043799998, 
              32.79458615000004
            ], 
            [
              -79.93488377599994, 
              32.793753338000045
            ], 
            [
              -79.93336686999999, 
              32.79425897400006
            ], 
            [
              -79.93247457199999, 
              32.79256360800008
            ], 
            [
              -79.93220688199995, 
              32.79217694500005
            ], 
            [
              -79.93180677999999, 
              32.79191600900003
            ]
          ]
        ]
      }, 
      "type": "Feature", 
      "properties": {
        "County": "Charleston", 
        "City": "Charleston", 
        "State": "SC", 
        "RegionID": "762415", 
        "Name": "Eastside"
      }
    }, 
    {
      "geometry": {
        "type": "Polygon", 
        "coordinates": [
          [
            [
              -79.93273168699994, 
              32.77627242300008
            ], 
            [
              -79.94075672199995, 
              32.77547860200008
            ], 
            [
              -79.94618310299995, 
              32.77494183500005
            ], 
            [
              -79.94715209799995, 
              32.77462425600004
            ], 
            [
              -79.94808484699996, 
              32.77479557700008
            ], 
            [
              -79.94927457799997, 
              32.77566170100005
            ], 
            [
              -79.95566247899995, 
              32.77988167500007
            ], 
            [
              -79.95342816499993, 
              32.78099645300006
            ], 
            [
              -79.95140086399994, 
              32.781567524000025
            ], 
            [
              -79.94953060799998, 
              32.782195701000035
            ], 
            [
              -79.94717494099996, 
              32.782823879000034
            ], 
            [
              -79.94565763799994, 
              32.78327034500006
            ], 
            [
              -79.94351374399997, 
              32.78385569300008
            ], 
            [
              -79.94100341299998, 
              32.78441486600008
            ], 
            [
              -79.93940917399993, 
              32.78478368200007
            ], 
            [
              -79.93771975599998, 
              32.78536665000007
            ], 
            [
              -79.93662916999995, 
              32.78353771700006
            ], 
            [
              -79.93460282099994, 
              32.78099645300006
            ], 
            [
              -79.93340833199994, 
              32.78144379200006
            ], 
            [
              -79.93334408599998, 
              32.781350993000046
            ], 
            [
              -79.93325128699996, 
              32.78082989100005
            ], 
            [
              -79.93317276499994, 
              32.780058945000064
            ], 
            [
              -79.93273168699994, 
              32.77627242300008
            ]
          ]
        ]
      }, 
      "type": "Feature", 
      "properties": {
        "County": "Charleston", 
        "City": "Charleston", 
        "State": "SC", 
        "RegionID": "762417", 
        "Name": "Harleston Village"
      }
    }, 
    {
      "geometry": {
        "type": "Polygon", 
        "coordinates": [
          [
            [
              -79.95488183999998, 
              32.812571751000064
            ], 
            [
              -79.95520006999999, 
              32.810474326000076
            ], 
            [
              -79.95468610599994, 
              32.80832329300006
            ], 
            [
              -79.95381046499995, 
              32.80411640600005
            ], 
            [
              -79.95346782199994, 
              32.80301233700004
            ], 
            [
              -79.95942599299997, 
              32.79998566200004
            ], 
            [
              -79.95990664399994, 
              32.80125153500006
            ], 
            [
              -79.96016838499997, 
              32.801156357000025
            ], 
            [
              -79.96409449499998, 
              32.79989524300004
            ], 
            [
              -79.96656913499999, 
              32.799181404000024
            ], 
            [
              -79.96854408699994, 
              32.798895869000035
            ], 
            [
              -79.96711641099995, 
              32.803464434000034
            ], 
            [
              -79.96645016199994, 
              32.80574871700003
            ], 
            [
              -79.96449900399995, 
              32.80884201600003
            ], 
            [
              -79.96373757599997, 
              32.81164978000004
            ], 
            [
              -79.96354721899996, 
              32.81341058100003
            ], 
            [
              -79.95830169699997, 
              32.81332611000005
            ], 
            [
              -79.95478128499997, 
              32.81323450100007
            ], 
            [
              -79.95488183999998, 
              32.812571751000064
            ]
          ]
        ]
      }, 
      "type": "Feature", 
      "properties": {
        "County": "Charleston", 
        "City": "Charleston", 
        "State": "SC", 
        "RegionID": "762424", 
        "Name": "Wagener Terrace"
      }
    }, 
    {
      "geometry": {
        "type": "Polygon", 
        "coordinates": [
          [
            [
              -79.95429032299995, 
              32.78692519700007
            ], 
            [
              -79.95559902599996, 
              32.79001849700006
            ], 
            [
              -79.95224398599998, 
              32.791255816000046
            ], 
            [
              -79.95133979099995, 
              32.78937604200007
            ], 
            [
              -79.95149961199996, 
              32.78922653300003
            ], 
            [
              -79.95161382599997, 
              32.78902665800007
            ], 
            [
              -79.95163286099995, 
              32.788579319000064
            ], 
            [
              -79.95152816499996, 
              32.788246195000056
            ], 
            [
              -79.95429032299995, 
              32.78692519700007
            ]
          ]
        ]
      }, 
      "type": "Feature", 
      "properties": {
        "County": "Charleston", 
        "City": "Charleston", 
        "State": "SC", 
        "RegionID": "762419", 
        "Name": "Gadsden Green"
      }
    }, 
    {
      "geometry": {
        "type": "Polygon", 
        "coordinates": [
          [
            [
              -79.94674706299998, 
              32.79461618100004
            ], 
            [
              -79.94734229699998, 
              32.794206348000046
            ], 
            [
              -79.94783919699995, 
              32.79381876600007
            ], 
            [
              -79.94853202699994, 
              32.793278358000066
            ], 
            [
              -79.94917448199999, 
              32.79246934100007
            ], 
            [
              -79.94991211499996, 
              32.79127961100005
            ], 
            [
              -79.95133979099995, 
              32.78937604200007
            ], 
            [
              -79.95224398599998, 
              32.791255816000046
            ], 
            [
              -79.95559902599996, 
              32.79001849700006
            ], 
            [
              -79.95429032299995, 
              32.78692519700007
            ], 
            [
              -79.95864473599994, 
              32.78487886100004
            ], 
            [
              -79.95897786099994, 
              32.78583064500003
            ], 
            [
              -79.95931098499995, 
              32.78647310000002
            ], 
            [
              -79.96014379699994, 
              32.78759144600008
            ], 
            [
              -79.96088142999997, 
              32.78809113300008
            ], 
            [
              -79.96195218699995, 
              32.78840046300007
            ], 
            [
              -79.96240428499993, 
              32.788448052000035
            ], 
            [
              -79.96516445999998, 
              32.789970907000054
            ], 
            [
              -79.95739551899999, 
              32.794038596000064
            ], 
            [
              -79.95063784999996, 
              32.79754235200005
            ], 
            [
              -79.94725901499999, 
              32.799184180000054
            ], 
            [
              -79.94542683099996, 
              32.79999319700005
            ], 
            [
              -79.94353515899996, 
              32.797942102000036
            ], 
            [
              -79.94339239099997, 
              32.79753759300007
            ], 
            [
              -79.94353515899996, 
              32.797014112000056
            ], 
            [
              -79.94436796999997, 
              32.79630027400003
            ], 
            [
              -79.94589082499994, 
              32.79520572200005
            ], 
            [
              -79.94674706299998, 
              32.79461618100004
            ]
          ]
        ]
      }, 
      "type": "Feature", 
      "properties": {
        "County": "Charleston", 
        "City": "Charleston", 
        "State": "SC", 
        "RegionID": "762420", 
        "Name": "Westside"
      }
    }, 
    {
      "geometry": {
        "type": "Polygon", 
        "coordinates": [
          [
            [
              -79.94733277899996, 
              32.78721073300005
            ], 
            [
              -79.94614304799995, 
              32.78762713800006
            ], 
            [
              -79.94625012399996, 
              32.787936468000055
            ], 
            [
              -79.94479865299996, 
              32.78850753900008
            ], 
            [
              -79.94232401299996, 
              32.78947122000005
            ], 
            [
              -79.93948055699997, 
              32.79050628600004
            ], 
            [
              -79.93629207999999, 
              32.785818748000054
            ], 
            [
              -79.93771975599998, 
              32.78536665000007
            ], 
            [
              -79.93940917399993, 
              32.78478368200007
            ], 
            [
              -79.94100341299998, 
              32.78441486600008
            ], 
            [
              -79.94351374399997, 
              32.78385569300008
            ], 
            [
              -79.94565763799994, 
              32.78327034500006
            ], 
            [
              -79.94733277899996, 
              32.78721073300005
            ]
          ]
        ]
      }, 
      "type": "Feature", 
      "properties": {
        "County": "Charleston", 
        "City": "Charleston", 
        "State": "SC", 
        "RegionID": "762421", 
        "Name": "Radcliffborough"
      }
    }, 
    {
      "geometry": {
        "type": "Polygon", 
        "coordinates": [
          [
            [
              -79.95091025799996, 
              32.812488967000036
            ], 
            [
              -79.94741381499995, 
              32.81239140400004
            ], 
            [
              -79.94566477699993, 
              32.81234260000008
            ], 
            [
              -79.94509370599997, 
              32.811343226000076
            ], 
            [
              -79.94609307999997, 
              32.81101010200007
            ], 
            [
              -79.94352326199999, 
              32.80884479200006
            ], 
            [
              -79.94304736999999, 
              32.80763126700003
            ], 
            [
              -79.94076308699994, 
              32.80408587000005
            ], 
            [
              -79.93957335599998, 
              32.80315788000007
            ], 
            [
              -79.94383259199998, 
              32.80153984700007
            ], 
            [
              -79.94390397499996, 
              32.800469089000046
            ], 
            [
              -79.94542683099996, 
              32.79999319700005
            ], 
            [
              -79.94595031199998, 
              32.800469089000046
            ], 
            [
              -79.94709245299998, 
              32.80203953400007
            ], 
            [
              -79.94809182699998, 
              32.80437140500004
            ], 
            [
              -79.94906740599998, 
              32.80746470500003
            ], 
            [
              -79.94968606599997, 
              32.80948724600006
            ], 
            [
              -79.95073302899993, 
              32.81101010200007
            ], 
            [
              -79.95296972199998, 
              32.81258054600005
            ], 
            [
              -79.95118420799997, 
              32.81249661100003
            ], 
            [
              -79.95091025799996, 
              32.812488967000036
            ]
          ]
        ]
      }, 
      "type": "Feature", 
      "properties": {
        "County": "Charleston", 
        "City": "Charleston", 
        "State": "SC", 
        "RegionID": "762422", 
        "Name": "East Central"
      }
    }, 
    {
      "geometry": {
        "type": "Polygon", 
        "coordinates": [
          [
            [
              -79.92545054599998, 
              32.77677494100004
            ], 
            [
              -79.92703526699995, 
              32.776660727000035
            ], 
            [
              -79.92700495399998, 
              32.776831722000054
            ], 
            [
              -79.93105936799998, 
              32.77643784500003
            ], 
            [
              -79.93106842699996, 
              32.77643694900007
            ], 
            [
              -79.93137095799995, 
              32.779343838000045
            ], 
            [
              -79.92780176599996, 
              32.78005767600007
            ], 
            [
              -79.92563050799998, 
              32.78029562200004
            ], 
            [
              -79.92545054599998, 
              32.77677494100004
            ]
          ]
        ]
      }, 
      "type": "Feature", 
      "properties": {
        "County": "Charleston", 
        "City": "Charleston", 
        "State": "SC", 
        "RegionID": "273792", 
        "Name": "French Quarter"
      }
    }, 
    {
      "geometry": {
        "type": "Polygon", 
        "coordinates": [
          [
            [
              -79.97373198299994, 
              32.775481014000036
            ], 
            [
              -79.97374893699998, 
              32.772342208000055
            ], 
            [
              -79.97357047699995, 
              32.76918942200007
            ], 
            [
              -79.97255920599997, 
              32.767018164000035
            ], 
            [
              -79.97397032599997, 
              32.76710501400004
            ], 
            [
              -79.97431296799994, 
              32.767200193000065
            ], 
            [
              -79.97465560999996, 
              32.76742862100008
            ], 
            [
              -79.97591196599996, 
              32.76746669200003
            ], 
            [
              -79.98061378099999, 
              32.76699080000003
            ], 
            [
              -79.98150845799995, 
              32.767124050000064
            ], 
            [
              -79.98217470699996, 
              32.76815197700006
            ], 
            [
              -79.97373198299994, 
              32.775481014000036
            ]
          ]
        ]
      }, 
      "type": "Feature", 
      "properties": {
        "County": "Charleston", 
        "City": "Charleston", 
        "State": "SC", 
        "RegionID": "762411", 
        "Name": "Wappo Heights"
      }
    }, 
    {
      "geometry": {
        "type": "Polygon", 
        "coordinates": [
          [
            [
              -79.97373198299994, 
              32.775481014000036
            ], 
            [
              -79.97303242099997, 
              32.77612346900003
            ], 
            [
              -79.97224719899998, 
              32.77646611100005
            ], 
            [
              -79.97126210199997, 
              32.77685158400004
            ], 
            [
              -79.96994863999998, 
              32.77686586100003
            ], 
            [
              -79.96200034799995, 
              32.76954634100008
            ], 
            [
              -79.96351725399995, 
              32.76901096300003
            ], 
            [
              -79.96545056599996, 
              32.76877301600007
            ], 
            [
              -79.96711618899997, 
              32.76871353000007
            ], 
            [
              -79.96851412199999, 
              32.768624300000056
            ], 
            [
              -79.96988231199998, 
              32.76847558400004
            ], 
            [
              -79.97080435399994, 
              32.76823763800007
            ], 
            [
              -79.97172639499996, 
              32.76779148900005
            ], 
            [
              -79.97229151699997, 
              32.76725611000006
            ], 
            [
              -79.97255920599997, 
              32.767018164000035
            ], 
            [
              -79.97357047699995, 
              32.76918942200007
            ], 
            [
              -79.97374893699998, 
              32.772342208000055
            ], 
            [
              -79.97373198299994, 
              32.775481014000036
            ]
          ]
        ]
      }, 
      "type": "Feature", 
      "properties": {
        "County": "Charleston", 
        "City": "Charleston", 
        "State": "SC", 
        "RegionID": "762412", 
        "Name": "Cresent"
      }
    }, 
    {
      "geometry": {
        "type": "Polygon", 
        "coordinates": [
          [
            [
              -79.94509370599997, 
              32.811343226000076
            ], 
            [
              -79.94566477699993, 
              32.81234260000008
            ], 
            [
              -79.94741381499995, 
              32.81239140400004
            ], 
            [
              -79.95091025799996, 
              32.812488967000036
            ], 
            [
              -79.95105879699997, 
              32.81401365500005
            ], 
            [
              -79.95105879699997, 
              32.814917851000075
            ], 
            [
              -79.95124915299994, 
              32.817368696000074
            ], 
            [
              -79.96354721899996, 
              32.81341058100003
            ], 
            [
              -79.96324163699995, 
              32.814608521000025
            ], 
            [
              -79.96286092299994, 
              32.81701177600007
            ], 
            [
              -79.96307507499995, 
              32.819224675000044
            ], 
            [
              -79.96331302099998, 
              32.82288904500007
            ], 
            [
              -79.96363035, 
              32.82499999100003
            ], 
            [
              -79.96018013199995, 
              32.82554726700005
            ], 
            [
              -79.96022772099997, 
              32.82621351600005
            ], 
            [
              -79.95287518699996, 
              32.82728427300003
            ], 
            [
              -79.95287560299994, 
              32.82730112200005
            ], 
            [
              -79.95202119399994, 
              32.827340123000056
            ], 
            [
              -79.95180704199998, 
              32.824184958000046
            ], 
            [
              -79.95163572099995, 
              32.821800738000036
            ], 
            [
              -79.95132163199997, 
              32.82064432000004
            ], 
            [
              -79.94293998099994, 
              32.82389109500008
            ], 
            [
              -79.93480707799995, 
              32.827100691000055
            ], 
            [
              -79.93468810499996, 
              32.82476881900004
            ], 
            [
              -79.93461672099994, 
              32.82279386700003
            ], 
            [
              -79.93442636399999, 
              32.82172310900006
            ], 
            [
              -79.93435497999997, 
              32.821199628000045
            ], 
            [
              -79.93428359699999, 
              32.820914092000066
            ], 
            [
              -79.93409323999998, 
              32.820652352000025
            ], 
            [
              -79.93402185599996, 
              32.82031922700003
            ], 
            [
              -79.93366493699995, 
              32.82008128100006
            ], 
            [
              -79.93304627699996, 
              32.81970056700004
            ], 
            [
              -79.93290350899997, 
              32.81946262100007
            ], 
            [
              -79.93297489299994, 
              32.81910570200006
            ], 
            [
              -79.93316524999994, 
              32.81841565800005
            ], 
            [
              -79.93316524999994, 
              32.81793976600005
            ], 
            [
              -79.93316524999994, 
              32.817178339000066
            ], 
            [
              -79.93276074099998, 
              32.81715454400006
            ], 
            [
              -79.93261797399998, 
              32.817035571000076
            ], 
            [
              -79.93230864399999, 
              32.81684521400007
            ], 
            [
              -79.93171377899995, 
              32.81601240300006
            ], 
            [
              -79.93035748599993, 
              32.81477508300003
            ], 
            [
              -79.93023851299995, 
              32.814465753000036
            ], 
            [
              -79.93023851299995, 
              32.81418021800005
            ], 
            [
              -79.93064302099998, 
              32.813180844000044
            ], 
            [
              -79.93133306499999, 
              32.81280013000003
            ], 
            [
              -79.93133306499999, 
              32.81232423800003
            ], 
            [
              -79.93188034099995, 
              32.81168178400003
            ], 
            [
              -79.93299868799994, 
              32.81139624800005
            ], 
            [
              -79.93635372799997, 
              32.81272874700005
            ], 
            [
              -79.94168371999996, 
              32.812395622000054
            ], 
            [
              -79.94180269299994, 
              32.81265736300003
            ], 
            [
              -79.94242135299999, 
              32.811705578000044
            ], 
            [
              -79.94365867299996, 
              32.81172937300005
            ], 
            [
              -79.94509370599997, 
              32.811343226000076
            ]
          ]
        ]
      }, 
      "type": "Feature", 
      "properties": {
        "County": "Charleston", 
        "City": "Charleston", 
        "State": "SC", 
        "RegionID": "762413", 
        "Name": "Silver Hill/Magnolia"
      }
    }, 
    {
      "geometry": {
        "type": "Polygon", 
        "coordinates": [
          [
            [
              -79.93629207999999, 
              32.785818748000054
            ], 
            [
              -79.93948055699997, 
              32.79050628600004
            ], 
            [
              -79.93729422899997, 
              32.79125668900008
            ], 
            [
              -79.93406286199996, 
              32.79245534200004
            ], 
            [
              -79.93374877299993, 
              32.791941379000036
            ], 
            [
              -79.93184996299993, 
              32.791284647000055
            ], 
            [
              -79.93152278699995, 
              32.791730796000024
            ], 
            [
              -79.93180677999999, 
              32.79191600900003
            ], 
            [
              -79.93150692399996, 
              32.792342476000044
            ], 
            [
              -79.93107862099998, 
              32.79212832500008
            ], 
            [
              -79.92936540899996, 
              32.788820874000066
            ], 
            [
              -79.93629207999999, 
              32.785818748000054
            ]
          ]
        ]
      }, 
      "type": "Feature", 
      "properties": {
        "County": "Charleston", 
        "City": "Charleston", 
        "State": "SC", 
        "RegionID": "762414", 
        "Name": "Mazyck-Wraggborough"
      }
    }, 
    {
      "geometry": {
        "type": "Polygon", 
        "coordinates": [
          [
            [
              -80.00182976899998, 
              32.823901515000045
            ], 
            [
              -79.99852048099996, 
              32.824820611000064
            ], 
            [
              -79.99794941, 
              32.824649290000025
            ], 
            [
              -79.99686437599996, 
              32.824977656000044
            ], 
            [
              -79.99686437599996, 
              32.825134700000035
            ], 
            [
              -79.99585072599996, 
              32.825620110000045
            ], 
            [
              -79.99513688799993, 
              32.82572004800005
            ], 
            [
              -79.99375204099994, 
              32.826733698000055
            ], 
            [
              -79.99346650599995, 
              32.82667659100008
            ], 
            [
              -79.99246713199994, 
              32.82713344700005
            ], 
            [
              -79.99209593599994, 
              32.82754747400003
            ], 
            [
              -79.99219587399995, 
              32.82797577700006
            ], 
            [
              -79.99295254199995, 
              32.828446910000025
            ], 
            [
              -79.99246713199994, 
              32.82880382900004
            ], 
            [
              -79.99023995699997, 
              32.82733332200007
            ], 
            [
              -79.99082530399994, 
              32.825463066000054
            ], 
            [
              -79.99135354499998, 
              32.82363564000008
            ], 
            [
              -79.99163908, 
              32.822593436000034
            ], 
            [
              -79.99364680199994, 
              32.82301159600007
            ], 
            [
              -79.99415179099998, 
              32.821051545000046
            ], 
            [
              -79.99426546199999, 
              32.82064165300005
            ], 
            [
              -79.99348078299994, 
              32.81970952900008
            ], 
            [
              -79.99777278799996, 
              32.817453175000026
            ], 
            [
              -79.99993809699998, 
              32.820867702000044
            ], 
            [
              -80.00182976899998, 
              32.823901515000045
            ]
          ]
        ]
      }, 
      "type": "Feature", 
      "properties": {
        "County": "Charleston", 
        "City": "Charleston", 
        "State": "SC", 
        "RegionID": "762409", 
        "Name": "Sandhurst"
      }
    }, 
    {
      "geometry": {
        "type": "Polygon", 
        "coordinates": [
          [
            [
              -79.93316342599996, 
              32.78516229400003
            ], 
            [
              -79.92969417099994, 
              32.78676129200005
            ], 
            [
              -79.92910882399997, 
              32.78687550600006
            ], 
            [
              -79.92908027099998, 
              32.78606173000003
            ], 
            [
              -79.92905171699994, 
              32.785390722000045
            ], 
            [
              -79.92895177999998, 
              32.78486248200005
            ], 
            [
              -79.92872335099997, 
              32.78450556300004
            ], 
            [
              -79.92845209299998, 
              32.78380600100007
            ], 
            [
              -79.92802378999994, 
              32.78313499300003
            ], 
            [
              -79.92776680799994, 
              32.78243543200006
            ], 
            [
              -79.93172147199994, 
              32.78204995900006
            ], 
            [
              -79.93186423999998, 
              32.783063610000056
            ], 
            [
              -79.93219260499995, 
              32.783634680000034
            ], 
            [
              -79.93274939899999, 
              32.78451984000003
            ], 
            [
              -79.93316342599996, 
              32.78516229400003
            ]
          ]
        ]
      }, 
      "type": "Feature", 
      "properties": {
        "County": "Charleston", 
        "City": "Charleston", 
        "State": "SC", 
        "RegionID": "762416", 
        "Name": "Ansonborough"
      }
    }, 
    {
      "geometry": {
        "type": "Polygon", 
        "coordinates": [
          [
            [
              -79.94733277899996, 
              32.78721073300005
            ], 
            [
              -79.95004813999998, 
              32.786354999000025
            ], 
            [
              -79.95050975599997, 
              32.787454310000044
            ], 
            [
              -79.95133979099995, 
              32.78937604200007
            ], 
            [
              -79.94991211499996, 
              32.79127961100005
            ], 
            [
              -79.94917448199999, 
              32.79246934100007
            ], 
            [
              -79.94853202699994, 
              32.793278358000066
            ], 
            [
              -79.94783919699995, 
              32.79381876600007
            ], 
            [
              -79.94734229699998, 
              32.794206348000046
            ], 
            [
              -79.94674706299998, 
              32.79461618100004
            ], 
            [
              -79.94609347599999, 
              32.794749737000075
            ], 
            [
              -79.94512265599997, 
              32.79512093300008
            ], 
            [
              -79.94326794999995, 
              32.795758281000076
            ], 
            [
              -79.94258266499997, 
              32.79631507500005
            ], 
            [
              -79.94239706699994, 
              32.79685759200004
            ], 
            [
              -79.94185455, 
              32.79691469900007
            ], 
            [
              -79.94118354199998, 
              32.797157404000075
            ], 
            [
              -79.94096811699995, 
              32.79690552900007
            ], 
            [
              -79.93914069099998, 
              32.79415011300006
            ], 
            [
              -79.93729422899997, 
              32.79125668900008
            ], 
            [
              -79.93948055699997, 
              32.79050628600004
            ], 
            [
              -79.94232401299996, 
              32.78947122000005
            ], 
            [
              -79.94479865299996, 
              32.78850753900008
            ], 
            [
              -79.94625012399996, 
              32.787936468000055
            ], 
            [
              -79.94614304799995, 
              32.78762713800006
            ], 
            [
              -79.94733277899996, 
              32.78721073300005
            ]
          ]
        ]
      }, 
      "type": "Feature", 
      "properties": {
        "County": "Charleston", 
        "City": "Charleston", 
        "State": "SC", 
        "RegionID": "762418", 
        "Name": "Cannonborough/Elliottbororugh"
      }
    }, 
    {
      "geometry": {
        "type": "Polygon", 
        "coordinates": [
          [
            [
              -79.94542683099996, 
              32.79999319700005
            ], 
            [
              -79.94725901499999, 
              32.799184180000054
            ], 
            [
              -79.95063784999996, 
              32.79754235200005
            ], 
            [
              -79.95191702399995, 
              32.80001483700005
            ], 
            [
              -79.95346782199994, 
              32.80301233700004
            ], 
            [
              -79.95381046499995, 
              32.80411640600005
            ], 
            [
              -79.95468610599994, 
              32.80832329300006
            ], 
            [
              -79.95520006999999, 
              32.810474326000076
            ], 
            [
              -79.95488183999998, 
              32.812571751000064
            ], 
            [
              -79.95296972199998, 
              32.81258054600005
            ], 
            [
              -79.95073302899993, 
              32.81101010200007
            ], 
            [
              -79.94968606599997, 
              32.80948724600006
            ], 
            [
              -79.94906740599998, 
              32.80746470500003
            ], 
            [
              -79.94809182699998, 
              32.80437140500004
            ], 
            [
              -79.94709245299998, 
              32.80203953400007
            ], 
            [
              -79.94595031199998, 
              32.800469089000046
            ], 
            [
              -79.94542683099996, 
              32.79999319700005
            ]
          ]
        ]
      }, 
      "type": "Feature", 
      "properties": {
        "County": "Charleston", 
        "City": "Charleston", 
        "State": "SC", 
        "RegionID": "762423", 
        "Name": "North Central"
      }
    }, 
    {
      "geometry": {
        "type": "Polygon", 
        "coordinates": [
          [
            [
              -79.92545054599998, 
              32.77677494100004
            ], 
            [
              -79.92557390799999, 
              32.77616765700003
            ], 
            [
              -79.92573608099997, 
              32.77571370100003
            ], 
            [
              -79.92604580799997, 
              32.77534861500004
            ], 
            [
              -79.92578437999998, 
              32.77351194000005
            ], 
            [
              -79.92639245, 
              32.77304344500004
            ], 
            [
              -79.92732587399996, 
              32.77306800900004
            ], 
            [
              -79.92884277999997, 
              32.76920138500003
            ], 
            [
              -79.93565398799996, 
              32.76961779100003
            ], 
            [
              -79.93711140699997, 
              32.769915224000044
            ], 
            [
              -79.94237596499994, 
              32.77226494100006
            ], 
            [
              -79.94416056099999, 
              32.77330595600006
            ], 
            [
              -79.94618310299995, 
              32.77494183500005
            ], 
            [
              -79.94075672199995, 
              32.77547860200008
            ], 
            [
              -79.93273168699994, 
              32.77627242300008
            ], 
            [
              -79.93106842699996, 
              32.77643694900007
            ], 
            [
              -79.93112510999998, 
              32.77642416300006
            ], 
            [
              -79.92700495399998, 
              32.776831722000054
            ], 
            [
              -79.92703526699995, 
              32.776660727000035
            ], 
            [
              -79.92545054599998, 
              32.77677494100004
            ]
          ]
        ]
      }, 
      "type": "Feature", 
      "properties": {
        "County": "Charleston", 
        "City": "Charleston", 
        "State": "SC", 
        "RegionID": "762425", 
        "Name": "Charlestowne"
      }
    }
  ]
}